thruster/__init__.py
thruster/server.py
thruster/worker.py
thruster/http2/__init__.py
thruster/http2/stream.py
thruster/http2/frames/__init__.py
thruster/http2/frames/abstract_frame.py
thruster/http2/frames/continuation_frame.py
thruster/http2/frames/data_frame.py
thruster/http2/frames/frame.py
thruster/http2/frames/frame_factory.py
thruster/http2/frames/goaway_frame.py
thruster/http2/frames/headers_frame.py
thruster/http2/frames/ping_frame.py
thruster/http2/frames/rst_frame.py
thruster/http2/frames/settings_frame.py
thruster/http2/frames/utils.py
thruster/http2/frames/window_update_frame.py
thruster-0.0.8.dist-info/LICENSE
thruster-0.0.8.dist-info/METADATA
thruster-0.0.8.dist-info/WHEEL
thruster-0.0.8.dist-info/entry_points.txt
thruster-0.0.8.dist-info/top_level.txt
thruster-0.0.8.dist-info/RECORD
