Metadata-Version: 2.1
Name: thruster
Version: 0.0.8
Summary: ASGI compatible HTTP/2 web server
Home-page: https://github.com/blackblood/Thruster
Author: Akshay Takkar
Author-email: akshay.takkar101@gmail.com
License: UNKNOWN
Platform: UNKNOWN
Classifier: Development Status :: 3 - Alpha
Classifier: Programming Language :: Python :: 3
Classifier: License :: OSI Approved :: MIT License
Classifier: Operating System :: OS Independent
